{
  "id": 1720,
  "category": "PyCon US 2013",
  "slug": "applied-parallel-computing-with-python",
  "title": "Applied Parallel Computing with Python",
  "summary": "In this tutorial we shall review three different and distinct approaches\nto parallel computing which can be used to solve problems in all manner\nof domains, including machine learning, natural language processing,\nfinance, and computer vision. The first two approaches to be reviewed\nwill be embarrassingly parallel in nature while the third approach will\nleverage fine-grain parallelism.\n",
  "description": "",
  "quality_notes": "",
  "language": "English",
  "copyright_text": "CC",
  "thumbnail_url": "http://i.ytimg.com/vi/vL0UtbJOKR0/hqdefault.jpg",
  "duration": null,
  "videos": [
    {
      "url": "http://s3.us.archive.org/nextdayvideo/psf/pycon2013/Applied_Parallel_Computing_wit.mp4?Signature=qOo29k1gptSaUt8SYe9GLGymYvs%3D&Expires=1364691416&AWSAccessKeyId=FEWGReWX3QbNk0h3",
      "type": "mp4",
      "length": null
    },
    {
      "url": "https://www.youtube.com/watch?v=vL0UtbJOKR0",
      "type": "youtube",
      "length": 0
    }
  ],
  "source_url": "https://www.youtube.com/watch?v=vL0UtbJOKR0",
  "tags": [
    "tutorial"
  ],
  "speakers": [
    "Ian Ozsvald",
    "Minesh B Amin"
  ],
  "recorded": "2013-03-14"
}