{
  "copyright_text": "Creative Commons Attribution license (reuse allowed)",
  "description": "From your first 'while True:' to your first framework.",
  "duration": 2148,
  "language": "eng",
  "recorded": "2016-07-16",
  "related_urls": [
    "https://2016.pygotham.org/talks/255/making-games/"
  ],
  "speakers": [
    "Piper Thunstrom"
  ],
  "tags": [
    "Games"
  ],
  "thumbnail_url": "https://i.ytimg.com/vi/Gm2sDARO2Yw/maxresdefault.jpg",
  "title": "Making Games",
  "videos": [
    {
      "type": "youtube",
      "url": "https://www.youtube.com/watch?v=Gm2sDARO2Yw"
    }
  ]
}
