{
  "id": 2431, 
  "category": "PyCon DE 2013", 
  "slug": "high-level-programmierung-in-der-raumfahrt", 
  "title": "High-Level Programmierung in der Raumfahrt", 
  "summary": "Field Programmable Gate Arrays (FPGA) werden normalerweise auf Registerebene programmiert mit Hardwarebeschreibungssprachen wie Verilog oder VHDL. Dies ist vergleichbar mit Assemblerprogrammierung eines Mikroprozessors. Die Sprache Handel-C (sic!) hat sich zum Ziel gemacht, Hardwarebeschreibung mit C-Syntax zu erm\u00f6glichen, unabh\u00e4ngig von der zu Grunde liegenden Hardware. Dazu mu\u00df das Problem die Synchronizit\u00e4t durch die inh\u00e4rente Parallelit\u00e4t einer Hardwarefunktion gel\u00f6st werden. Mit Handel-C ist es nun m\u00f6glich, einen Algorithmus in C zu schreiben, auf einem Rechner zu simulieren und anschlie\u00dfend aus dem identischen Quellcode eine Hardwareimplementierung zu synthetisieren. Dabei gehen die Vorteile einer Hochsprache nicht verloren, im Gegenteil: durch den global optimierenden Compiler werden weniger Ressourcen auf dem FPGA ben\u00f6tigt. Zusammen mit Bibliotheken f\u00fcr Fest- und Flie\u00dfkommaarithmetik, Graphikausgabe und Tastatur bedient sich ein FPGA dann wie ein embedded Prozessor mit einem Geschwindigkeitszuwachs von Faktor 100.", 
  "description": "", 
  "quality_notes": "", 
  "language": "German", 
  "copyright_text": "", 
  "thumbnail_url": "http://i1.ytimg.com/vi/2w7K5wUL9IE/hqdefault.jpg", 
  "duration": 60, 
  "videos": [
    {
      "url": "https://www.youtube.com/watch?v=2w7K5wUL9IE", 
      "length": 0, 
      "type": "youtube"
    }
  ], 
  "source_url": "https://www.youtube.com/watch?v=2w7K5wUL9IE", 
  "tags": [], 
  "speakers": [
    "Felix Huber"
  ], 
  "recorded": "2013-10-17"
}