{
  "description": "\ud83d\udce3Queremos invitarlos a la Reuni\u00f3n #20 de Python Pereira \ud83c\udf89\n\nEn esta ocasi\u00f3n contaremos con dos interesantes charlas \ud83d\udc0d\ud83d\udcbb:\n\n\n\n\ud83d\udc49 Como iniciar en el mundo de la automatizaci\u00f3n de pruebas por Daniela Zuluaga\n\ud83d\udd17 Material: https://github.com/Nany262/automatizacion-basica-python\n\n\n\n\ud83d\udc49 Web scraping con python por German David G\u00f3mez Guti\u00e9rrez (30:39)\n\n\ud83d\udd17 Material: https://github.com/germang2/web_scraping_images\nhttps://docs.google.com/presentation/d/1Ez07WqNU3tztPgmwd9MmRVTXyfdlHbXcrWJ51FR7Qg8/edit?usp=sharing\n\n\n\n\u00a0\ud83d\udcc4P.D.\ud83d\udcc4 Si estas interesado en participar como ponente o patrocinar nuestros Meetups, cont\u00e1ctanos por este medio o escr\u00edbenos a nuestro buz\u00f3n en python.pereira@gmail.com .",
  "duration": 4069,
  "language": "eng",
  "recorded": "2022-04-27",
  "related_urls": [
    {
      "label": "https://docs.google.com/presentation/d/1Ez07WqNU3tztPgmwd9MmRVTXyfdlHbXcrWJ51FR7Qg8/edit?usp=sharing",
      "url": "https://docs.google.com/presentation/d/1Ez07WqNU3tztPgmwd9MmRVTXyfdlHbXcrWJ51FR7Qg8/edit?usp=sharing"
    },
    {
      "label": "https://github.com/germang2/web_scraping_images",
      "url": "https://github.com/germang2/web_scraping_images"
    },
    {
      "label": "https://github.com/Nany262/automatizacion-basica-python",
      "url": "https://github.com/Nany262/automatizacion-basica-python"
    }
  ],
  "speakers": [
    "TODO"
  ],
  "tags": [
    "Python",
    "Tecnolog\u00eda",
    "buenas practicas",
    "docker"
  ],
  "thumbnail_url": "https://i.ytimg.com/vi/KysExEDT6ZU/maxresdefault.jpg",
  "title": "Automatizaci\u00f3n de Pruebas y Web Scraping \ud83d\udc0d\ud83d\udcbb",
  "videos": [
    {
      "type": "youtube",
      "url": "https://www.youtube.com/watch?v=KysExEDT6ZU"
    }
  ]
}
