{
  "description": "Encuentra las diapositivas en https://pybaq.co/eventos/\n\n0:00:00 Inicio de la transmisi\u00f3n\n0:05:03 Inicio charla\n0:52:40 Demostraci\u00f3n\n1:08:36 Preguntas y Respuestas",
  "duration": 5609,
  "language": "eng",
  "recorded": "2020-10-30",
  "related_urls": [
    {
      "label": "Website",
      "url": "https://pybaq.co/"
    },
    {
      "label": "https://pybaq.co/eventos/",
      "url": "https://pybaq.co/eventos/"
    }
  ],
  "speakers": [
    "TODO"
  ],
  "tags": [
    "#devops",
    "#python #redes #automatizaci\u00f3n"
  ],
  "thumbnail_url": "https://i.ytimg.com/vi/XUiIGJNdqlo/sddefault.jpg?v=5f889bba",
  "title": "PyBAQ - Automatizaci\u00f3n de Redes con Python",
  "videos": [
    {
      "type": "youtube",
      "url": "https://www.youtube.com/watch?v=XUiIGJNdqlo"
    }
  ]
}
