{
  "description": "",
  "duration": 1261,
  "language": "spa",
  "recorded": "2024-06-07",
  "related_urls": [
    {
      "label": "Conference Website",
      "url": "https://2024.pycon.co/"
    }
  ],
  "speakers": [
    "TODO"
  ],
  "tags": [],
  "thumbnail_url": "https://i.ytimg.com/vi_webp/e7SKRYoMNL8/maxresdefault.webp",
  "title": "Interview Lorena Barba - Keynote Pycon Colombia 2024",
  "videos": [
    {
      "type": "youtube",
      "url": "https://www.youtube.com/watch?v=e7SKRYoMNL8"
    }
  ]
}
