{
  "id": 636,
  "category": "PyCon US 2012",
  "slug": "practical-machine-learning-in-python",
  "title": "Practical Machine Learning in Python",
  "summary": "There are a plethora of options when it comes to deciding how to add a\nmachine learning component to your python application. In this talk,\nI'll discuss why python as a language is well-suited to solving these\nparticular problems, the tradeoffs of different machine learning\nsolutions for python applications, and some tricks you can use to get\nthe most out of whatever package you decide to use.\n",
  "description": "",
  "quality_notes": "",
  "language": "English",
  "copyright_text": "",
  "thumbnail_url": "http://img.youtube.com/vi/__s45TTXxps/hqdefault.jpg",
  "duration": null,
  "videos": [
    {
      "url": "https://www.youtube.com/watch?v=__s45TTXxps",
      "type": "youtube",
      "length": 0
    }
  ],
  "source_url": "https://www.youtube.com/watch?v=__s45TTXxps",
  "tags": [],
  "speakers": [
    "Matt Spitz"
  ],
  "recorded": "2012-03-09"
}