{
  "copyright_text": null,
  "description": "",
  "duration": 173,
  "language": "spa",
  "recorded": "2017-06-10T18:30:00+02:00",
  "related_urls": [
    {
      "label": "Event schedule",
      "url": "https://pyday2017.python-vigo.es/es/schedule/"
    },
    {
      "label": "Miguel Grinberg - Asynchronous Python for the Complete Beginner",
      "url": "https://speakerdeck.com/pycon2017/miguel-grinberg-asynchronous-python-for-the-complete-beginner"
    }
  ],
  "speakers": [
    "Ruben Gonzalez"
  ],
  "tags": [
    "lightning talks",
    "pyday",
    "Galicia"
  ],
  "thumbnail_url": "https://replay.teltek.es/uploads/pic/series/593ea555a7bc288d038b45c8/video/594a2171a7bc28c01b8b45b2/170621100756.jpg",
  "title": "Lightning Talks 1: Processes vs. Threads vs. Async",
  "videos": [
    {
      "type": "teletek.es",
      "url": "https://replay.teltek.es/video/594a2171a7bc28c01b8b45b2"
    }
  ]
}
