{"whiteboard": "", "video_mp4_download_only": false, "video_webm_download_only": false, "duration": null, "video_ogv_download_only": false, "category": "PyCon CA 2012", "speakers": ["Diego Mu\u00f1oz Escalante"], "title": "An Ember.js adapter for Django", "quality_notes": "", "video_flv_length": null, "recorded": "2012-11-11", "video_mp4_length": null, "description": "", "video_mp4_url": "http://s3.us.archive.org/nextdayvideo/pyconca/pyconca2012/An_Emberjs_adapter_for_Django.mp4?Signature=LgqYMSIM%2BF%2B10lOFmSQyZIoO%2BfI%3D&Expires=1352841411&AWSAccessKeyId=FEWGReWX3QbNk0h3", "tags": [], "copyright_text": "", "related_urls": [], "video_flv_download_only": false, "source_url": "https://www.youtube.com/watch?v=2SXtNV_knDk", "video_webm_url": "", "video_ogv_length": null, "video_ogv_url": "", "language": "English", "video_webm_length": null, "summary": "Ember is a JS framework based on established conventions that allows writing\ncomplex applications with a small amount of code. Ember-data is the component\nthat connects this framework with a REST API. Unfortunately, the conventions\nfollowed by its community are not compatible with Tastypie, one of the most\nwidely used Django libraries. This adapter makes all these technologies work\ntogether.\n\n", "thumbnail_url": "http://i3.ytimg.com/vi/2SXtNV_knDk/hqdefault.jpg", "video_flv_url": ""}