{
  "description": "The web wouldn\u2019t be the web without URLs. Unlike most web technology, URLs are not designed primarily to connect computers to each other. URLs connect us, people, to our software. This is an approachable engineering introduction to the often-overlooked URL, its evolution, and its many moving parts.",
  "language": "eng",
  "recorded": "2017-05-27",
  "related_urls": [
    {
      "label": "schedule",
      "url": "https://pyconweb.com/#schedule"
    }
  ],
  "speakers": [
    "Mahmoud Hashemi"
  ],
  "tags": [],
  "thumbnail_url": "https://i.ytimg.com/vi/EIkmADO-r10/hqdefault.jpg",
  "title": "URLs: In Plain View",
  "videos": [
    {
      "type": "youtube",
      "url": "https://www.youtube.com/watch?v=EIkmADO-r10"
    }
  ]
}
