{
  "description": "Speaker: Yuta Kanzawa\n\nTrack:PyData\nR and Python are partially overlapping but different as a whole: community and language. Still, comparing them in their common fields such as data wrangling and visualisation, useRs and Pythonistas will deepen mutual understanding.\n\nRecorded at the PyConDE & PyData Berlin 2019 conference.\nhttps://pycon.de\n\nMore details at the conference page: https://de.pycon.org/program/9D3JQC\nTwitter:  https://twitter.com/pydataberlin\nTwitter:  https://twitter.com/pyconde",
  "language": "eng",
  "recorded": "2019-10-11",
  "related_urls": [
    {
      "label": "Conference Schedule",
      "url": "https://de.pycon.org/program/9D3JQC"
    }
  ],
  "speakers": [
    "Yuta Kanzawa"
  ],
  "thumbnail_url": "https://i.ytimg.com/vi/SwH88oA36qY/hqdefault.jpg",
  "title": "Friend or Foe: Comparison of R & Python in Data Wrangling & Visualization",
  "videos": [
    {
      "type": "youtube",
      "url": "https://www.youtube.com/watch?v=SwH88oA36qY"
    }
  ]
}
