{
  "copyright_text": null,
  "description": "",
  "duration": 2017,
  "language": "kor",
  "recorded": "2018-08-18",
  "related_urls": [
    {
      "label": "Conference schedule",
      "url": "https://www.pycon.kr/2018/en/program/schedule/"
    }
  ],
  "speakers": [],
  "tags": [],
  "thumbnail_url": "https://i.ytimg.com/vi/gfOyxIbKH-Q/maxresdefault.jpg",
  "title": "\uc778\uacf5\uc9c0\ub2a5 \uc288\ud37c\ub9c8\ub9ac\uc624\uc758 \uac70\uc758 \ubaa8\ub4e0\uac83 - \uc815\uc6d0\uc11d",
  "videos": [
    {
      "type": "youtube",
      "url": "https://www.youtube.com/watch?v=gfOyxIbKH-Q"
    }
  ]
}
