{
  "alias": "video/3587/importazione-dati-in-django",
  "category": "PyCon Italia 2015",
  "copyright_text": "",
  "description": "L\u2019importazione dati da una fonte esterna, in un Database gi\u00e0 esistente,\n\u00e8 un task che nasconde numerose insidie. Generalmente, i dati da\nimportare risiedono in un file csv, o comunque possono essere ricondotti\na questo formato. Esistono numerose app django che si occupano di\nimportazione dati da csv, ma purtroppo non esiste ancora un prodotto che\nsia in grado di trattare la grande variet\u00e0 di scenari possibili. il talk\npresenter\u00e0 scenari comuni di importazione dati, concentrandosi sui casi\nche si presentano pi\u00f9 di frequente e mostrer\u00e0 come possano essere\nrisolti e schedulati, in maniera sufficientemente economica, utilizzando\nuna app Django creata dall\u2019autore. Verranno anche parzialmente discussi\ncasi di reingegnerizzazione di applicazioni esistenti con l\u2019importazione\ndi dump di DB con uno Schema differente .\n",
  "duration": 2350,
  "id": 3587,
  "language": "ita",
  "quality_notes": "",
  "recorded": "2015-05-30",
  "slug": "importazione-dati-in-django",
  "speakers": [
    "Gianluca Esposito"
  ],
  "summary": "",
  "tags": [],
  "thumbnail_url": "https://i.ytimg.com/vi/gj3un9L8cO8/maxresdefault.jpg",
  "title": "Importazione dati in Django",
  "videos": [
    {
      "length": 0,
      "type": "youtube",
      "url": "https://www.youtube.com/watch?v=gj3un9L8cO8"
    }
  ]
}