{
  "copyright_text": null,
  "description": "How does The New York Times use data science to further its mission? We'll talk about the use of machine learning throughout the company, from social media promotion to targeted advertising to content recommendations, and the cross-team collaborations that make it possible.",
  "duration": 2289,
  "language": "eng",
  "recorded": "2019-11-05",
  "related_urls": [
    {
      "label": "Conference schedule",
      "url": "https://pydata.org/nyc2019/schedule/"
    }
  ],
  "speakers": [
    "Chris Wiggins",
    "Anne Bauer"
  ],
  "tags": [
    "keynote"
  ],
  "thumbnail_url": "https://i.ytimg.com/vi/WRSi5KabLwc/maxresdefault.jpg",
  "title": "Data science at The New York Times: a mission-driven approach to personalizing the customer journey",
  "videos": [
    {
      "type": "youtube",
      "url": "https://www.youtube.com/watch?v=WRSi5KabLwc"
    }
  ]
}
