{
  "copyright_text": null,
  "description": "'Don't show up to this talk, it's going to be stupid. You won't learn anything, and if you do learn something, I promise it will be dumb.' - Diego Torres Quintanilla, PyData NYC Executive Chair",
  "duration": 1130,
  "language": "eng",
  "recorded": "2019-11-05",
  "related_urls": [
    {
      "label": "Conference schedule",
      "url": "https://pydata.org/nyc2019/schedule/"
    }
  ],
  "speakers": [
    "James Powell"
  ],
  "tags": [],
  "thumbnail_url": "https://i.ytimg.com/vi/xT1chRYlHIU/maxresdefault.jpg",
  "title": "Sloth & ENVy",
  "videos": [
    {
      "type": "youtube",
      "url": "https://www.youtube.com/watch?v=xT1chRYlHIU"
    }
  ]
}
