{
  "id": 997,
  "category": "PyCon AU 2011",
  "slug": "how-python-evolves-and-how-you-can-help-make-it",
  "title": "How Python Evolves (and How You Can Help Make It Happen)",
  "alias": "video/997/how-python-evolves-and-how-you-can-help-make-it",
  "summary": "The CPython reference interpreter lies at the heart of a much wider\nPython ecosystem. The decisions that shape the future development of\nCPython ripple out and have a broad impact on the entire Python\ncommunity. This talk covers the special place CPython occupies in the\nbroader Python community, how the decisions that affect CPython's\ndevelopment are made, and how new developers can become involved in that\nprocess..\n",
  "description": "",
  "quality_notes": "",
  "language": "English",
  "copyright_text": "Creative Commons Attribution license",
  "thumbnail_url": "http://i.ytimg.com/vi/UZIq_9KgFEY/hqdefault.jpg",
  "duration": null,
  "videos": [
    {
      "url": "http://www.youtube.com/watch?v=UZIq_9KgFEY",
      "type": "youtube",
      "length": 0
    }
  ],
  "source_url": "http://www.youtube.com/watch?v=UZIq_9KgFEY",
  "tags": [
    "cpython"
  ],
  "speakers": [
    "Nick Coghlan"
  ],
  "recorded": "2011-08-22"
}