{
  "alias": "video/2917/ein-eigener-sourceforge-mit-allura",
  "category": "PyCon DE 2011",
  "copyright_text": "https://www.youtube.com/t/terms",
  "description": "",
  "duration": null,
  "id": 2917,
  "language": "deu",
  "quality_notes": "",
  "recorded": "2011-10-07",
  "slug": "ein-eigener-sourceforge-mit-allura",
  "speakers": [
    "Andreas Schreiber"
  ],
  "summary": "Allura ist die Implementierung eines Software-Forge, d.h. einer\nWeb-Plattform zum gemeinschaftlichen Entwickeln von Software. Im Vortrag\nwird die Architektur von Allura vorgestellt und die Installation zum\nBetrieb eigener Software-Forges beschrieben. Anhand eines Beispiels wird\nerl\u00e4utert, wie Allura an die eigene Firma oder Organisation angepasst\nwerden kann.\n",
  "tags": [],
  "thumbnail_url": "https://i1.ytimg.com/vi/6YbBmqUnoQM/hqdefault.jpg",
  "title": "Ein eigener \"SourceForge\" mit Allura",
  "videos": [
    {
      "length": 0,
      "type": "youtube",
      "url": "https://www.youtube.com/watch?v=6YbBmqUnoQM"
    }
  ]
}
