{
  "alias": "video/117/volker-kuhlmann---rapid-gui-application-developme",
  "category": "Kiwi PyCon 2009",
  "copyright_text": "Creative Commons Attribution-NonCommercial-ShareAlike 3.0",
  "description": "Rapid GUI application development with Python\n\nPresented by Volker Kuhlmann\n\nAbstract\n\nOptions and tools for rapid desktop GUI application development using\npython are examined, and how they compare to competing languages and\nplatforms.\n\nOutline\n\nExamine GUI options for python including Qt, and their performance with\nrespect to ease of use, runtime, and platform portability. Examine\noptions for the tool chain (IDE, editor, debugger, programming aids) and\ncharacterise their ease of use and level of sophistication, and compare\nwith commonly used equivalents, both open source and not open source.\nDemonstrate a sample program.\n",
  "duration": null,
  "id": 117,
  "language": "eng",
  "quality_notes": "",
  "recorded": "2009-11-07",
  "slug": "volker-kuhlmann---rapid-gui-application-developme",
  "speakers": [
    "Volker Kuhlmann"
  ],
  "summary": "",
  "tags": [
    "gui",
    "kiwipycon",
    "kiwipycon2009",
    "qt"
  ],
  "thumbnail_url": "https://archive.org/services/img/pyvideo_117___volker-kuhlmann-rapid-gui-application-development-with-python",
  "title": "Volker Kuhlmann - Rapid GUI application development with python",
  "videos": [
    {
      "type": "archive.org",
      "url": "https://archive.org/details/pyvideo_117___volker-kuhlmann-rapid-gui-application-development-with-python"
    }
  ]
}
