{
  "copyright_text": null,
  "description": "",
  "duration": 1330,
  "language": "eng",
  "recorded": "2019-10-12",
  "related_urls": [
    {
      "label": "Conference schedule",
      "url": "http://pycon2019.python.ie/schedule/"
    }
  ],
  "speakers": [],
  "tags": [],
  "thumbnail_url": "https://i.ytimg.com/vi/2VEgZS3af4k/maxresdefault.jpg",
  "title": "PyCon Ireland 2019 - Will somebody please tell me what's going on? - Stephen Finucane",
  "videos": [
    {
      "type": "youtube",
      "url": "https://www.youtube.com/watch?v=2VEgZS3af4k"
    }
  ]
}
