{
  "copyright_text": null,
  "description": "The Carpentries, an open source project that develops training and instructing resources for researchers, has developed a membership program that is key to our sustainability and mission. This program creates communities of open source practices at organisations around the world and supports the open materials and forums of The Carpentries. We have learned from our various successes and challenges, continue to assess the effectiveness of this program, and are preparing for the challenges of adapting this program to be effective in our rapidly growing and diversifying community.\nSee the full SciPy 2019 playlist at https://www.youtube.com/playlist?list=PLYx7XA2nY5GcDQblpQ_M1V3PQPoLWiDAC\nConnect with us!\n*****************\nhttps://twitter.com/enthought\nhttps://www.facebook.com/Enthought/\nhttps://www.linkedin.com/company/enthought",
  "duration": 1675,
  "language": "eng",
  "recorded": "2019-07-13",
  "related_urls": [
    {
      "label": "Conference schedule",
      "url": "https://www.scipy2019.scipy.org/confschedule"
    },
    {
      "label": "https://twitter.com/enthought",
      "url": "https://twitter.com/enthought"
    },
    {
      "label": "https://www.linkedin.com/company/enthought",
      "url": "https://www.linkedin.com/company/enthought"
    },
    {
      "label": "https://www.youtube.com/playlist?list=PLYx7XA2nY5GcDQblpQ_M1V3PQPoLWiDAC",
      "url": "https://www.youtube.com/playlist?list=PLYx7XA2nY5GcDQblpQ_M1V3PQPoLWiDAC"
    },
    {
      "label": "https://www.facebook.com/Enthought/",
      "url": "https://www.facebook.com/Enthought/"
    }
  ],
  "speakers": [
    "Kari Jordan",
    "Elizabeth Williams"
  ],
  "tags": [],
  "thumbnail_url": "https://i.ytimg.com/vi/qvDFVQDABiM/maxresdefault.jpg",
  "title": "Experience Building Local Communities of Open Source Practices Users through The Carpentries' Membership Program",
  "videos": [
    {
      "type": "youtube",
      "url": "https://www.youtube.com/watch?v=qvDFVQDABiM"
    }
  ]
}
