{
  "description": "Intake is a simple library providing one interface for cataloging, finding, describing and reading any data locally, in the cloud, or on an Intake server. Intake separates the definition of data sources from their analysis, so that Data Engineers and Data Scientists can get on with their jobs.\n\nPresentation page -- https://2018.pycon.ca/talks/talk-PC-55191/",
  "recorded": "2018-11-11",
  "speakers": [
    "Martin Durant"
  ],
  "thumbnail_url": "https://i.ytimg.com/vi/IzwLnnVsEG4/hqdefault.jpg",
  "title": "Intake - taking the pain out of data access",
  "videos": [
    {
      "type": "youtube",
      "url": "https://www.youtube.com/watch?v=IzwLnnVsEG4"
    }
  ]
}
