{
  "alias": "video/1108/python-tips-tricks-and-idioms",
  "category": "EuroPython 2011",
  "copyright_text": "Standard YouTube License",
  "description": "Dozens of little insights into the language. A whirlwind tour of nifty\ntricks, little known features, and common patterns.\n",
  "duration": null,
  "id": 1108,
  "language": "eng",
  "quality_notes": "",
  "recorded": "2011-07-13",
  "slug": "python-tips-tricks-and-idioms",
  "speakers": [
    "Raymond Hettinger"
  ],
  "summary": "[EuroPython 2011] Raymond Hettinger - 23 June 2011 in \"Track Spaghetti\"\n",
  "tags": [],
  "thumbnail_url": "https://i.ytimg.com/vi/JbNG3rVLJvA/hqdefault.jpg",
  "title": "Python Tips, Tricks, and Idioms",
  "videos": [
    {
      "length": 0,
      "type": "youtube",
      "url": "https://www.youtube.com/watch?v=JbNG3rVLJvA"
    }
  ]
}
