{
  "description": "Channels is the most exciting thing to happen to Django since, well,\nDjango! It is both an elegant and backwards compatible extension of the\ncore Django request response model to allow direct support of WebSockets\nand lightweight async tasks. This talk will cover the current state of\nChannels, work through an asynchronous task example, touch on deployment\nand point towards other resources.\n\nAlbert O'Connor Bio\n-------------------\n\nFreelance Django developer with over 5 years over independent\ncontracting for business, startups and institutions. Instigator\nincluding WatPy the Waterloo Region Python Users Group.\n",
  "duration": 1338,
  "language": "eng",
  "recorded": "2016-11-12",
  "speakers": [
    "Albert O\u2019Connor"
  ],
  "thumbnail_url": "https://i.ytimg.com/vi/Dv1bpmYV0vU/maxresdefault.jpg",
  "title": "Async tasks with Django Channels",
  "videos": [
    {
      "type": "youtube",
      "url": "https://www.youtube.com/watch?v=Dv1bpmYV0vU"
    }
  ]
}
