{
  "copyright_text": null,
  "description": "",
  "duration": 1041,
  "language": "spa",
  "recorded": "2020-04-17",
  "related_urls": [
    {
      "label": "Conference schedule",
      "url": "https://us.pycon.org/2020/online/"
    }
  ],
  "speakers": [
    "Renne Silva Gomes de Oliveira Rocha"
  ],
  "tags": [
    "charla"
  ],
  "thumbnail_url": "https://i.ytimg.com/vi/KJrgcTfGZig/maxresdefault.jpg",
  "title": "Si no est\u00e1 documentado, su proyecto no existe.",
  "videos": [
    {
      "type": "youtube",
      "url": "https://www.youtube.com/watch?v=KJrgcTfGZig"
    }
  ]
}
