{
  "description": "pyAgrum est un module de gestion et de calcul de mod\u00e8les graphiques, en\nparticulier probabilistes. Lors de cette pr\u00e9sentation, nous ferons le tour des\nfonctionnalit\u00e9s propos\u00e9es par pyAgrum pour l'utilisation de r\u00e9seaux bay\u00e9siens.\n\u00c0 l\u2019aide de Python Notebooks, nous monterons en live comment exploiter pyAgrum\net les r\u00e9seaux bay\u00e9siens pour l\u2019aide \u00e0 la d\u00e9cision, la ma\u00eetrise du risque ou\nencore pour l\u2019enseignement. La mod\u00e9lisation sera abord\u00e9e avec un accent sur\nles diff\u00e9rentes structures de donn\u00e9es utilis\u00e9es pour repr\u00e9senter les tables\nmultidimensionnelle. \u00c0 l\u2019aide des algorithmes d\u2019inf\u00e9rence probabiliste, nous\nmontrerons comment r\u00e9aliser de l\u2019analyse de sensibilit\u00e9. Finalement, nous\nmontrerons comment utiliser pyAgrum pour de l\u2019apprentissage de structure et de\nparam\u00e8tres de r\u00e9seaux bay\u00e9siens. pyAgrum est essentiellement un wrapper de la\nlibrairie C++ aGrUM, qui impl\u00e9mente des mod\u00e8les graphiques pour l\u2019aide \u00e0 la\nd\u00e9cision; ce qui offre \u00e0 pyAgrum des performances \u00e9lev\u00e9es pour tous ses\nalgorithmes d\u2019inf\u00e9rence et d'apprentissage.\nhttp://pyagrum.lip6.fr\n",
  "recorded": "2016-10-15",
  "speakers": [
    "Lionel Torti"
  ],
  "thumbnail_url": "https://i.ytimg.com/vi/rtLMYa7wFvo/maxresdefault.jpg",
  "title": "Mod\u00e9lisation, inf\u00e9rence et apprentissage de R\u00e9seaux Bay\u00e9sien avec pyAgrum",
  "videos": [
    {
      "type": "youtube",
      "url": "https://www.youtube.com/watch?v=rtLMYa7wFvo"
    }
  ]
}
