{
  "copyright_text": null,
  "description": "",
  "duration": 1811,
  "language": null,
  "recorded": "2017-06-09",
  "related_urls": [
    {
      "label": "Conference schedule",
      "url": "https://tw.pycon.org/2017/en-us/events/schedule/"
    }
  ],
  "speakers": [
    "Brad Chang"
  ],
  "tags": [],
  "thumbnail_url": "https://i.ytimg.com/vi/AosR-pElbOQ/maxresdefault.jpg",
  "title": "Brad Chang - How we use Deep Learning to classify more than 180,000 photos a day on PhotoGrid",
  "videos": [
    {
      "type": "youtube",
      "url": "https://www.youtube.com/watch?v=AosR-pElbOQ"
    }
  ]
}
