{
  "copyright_text": null,
  "description": "",
  "duration": 2081,
  "language": "eng",
  "recorded": "2019-05-10",
  "related_urls": [
    {
      "label": "Conference schedule",
      "url": "https://pydata.org/amsterdam2019/schedule/"
    }
  ],
  "speakers": [
    "Alexander Hendorf"
  ],
  "tags": [
    "pydata"
  ],
  "thumbnail_url": "https://i.ytimg.com/vi/ijhZR43TOwc/maxresdefault.jpg",
  "title": "Speech Synthesis with Tacotron2 and PyTorch",
  "videos": [
    {
      "type": "youtube",
      "url": "https://www.youtube.com/watch?v=ijhZR43TOwc"
    }
  ]
}
