{
  "copyright_text": "This video is licensed under the CC BY-NC-SA 3.0 license: https://creativecommons.org/licenses/by-nc-sa/3.0/\nPlease see our speaker release agreement for details: https://ep2020.europython.eu/events/speaker-release-agreement/\n",
  "description": "\"30 Golden Rules of Deep Learning Performance\nEuroPython 2020 - Keynote - 2020-07-24 - Microsoft\nOnline\n\nBy Siddha Ganju\n\n\n\n\nLicense: This video is licensed under the CC BY-NC-SA 3.0 license: https://creativecommons.org/licenses/by-nc-sa/3.0/\nPlease see our speaker release agreement for details: https://ep2020.europython.eu/events/speaker-release-agreement/\n\n\"",
  "duration": 2427,
  "language": "eng",
  "recorded": "2020-07-23",
  "related_urls": [
    {
      "label": "Conference Website",
      "url": "https://ep2020.europython.eu/"
    },
    {
      "label": "https://ep2020.europython.eu/events/speaker-release-agreement/",
      "url": "https://ep2020.europython.eu/events/speaker-release-agreement/"
    },
    {
      "label": "https://creativecommons.org/licenses/by-nc-sa/3.0/",
      "url": "https://creativecommons.org/licenses/by-nc-sa/3.0/"
    }
  ],
  "speakers": [
    "Siddha Ganju"
  ],
  "tags": [],
  "thumbnail_url": "https://i.ytimg.com/vi/B98m2k7CKYc/sddefault.jpg",
  "title": "30 Golden Rules of Deep Learning Performance",
  "videos": [
    {
      "type": "youtube",
      "url": "https://www.youtube.com/watch?v=B98m2k7CKYc"
    }
  ]
}
