{
  "alias": "video/1654/a-beginners-introduction-to-pydata-how-to-build",
  "category": "PyCon US 2013",
  "copyright_text": "CC",
  "description": "",
  "duration": null,
  "id": 1654,
  "language": "eng",
  "quality_notes": "",
  "recorded": "2013-03-13",
  "slug": "a-beginners-introduction-to-pydata-how-to-build",
  "speakers": [
    "Amr Hiram",
    "Diego Maniloff",
    "Zach Howard"
  ],
  "summary": "In this tutorial we'll set ourselves the goal of building a minimal\nrecommendation engine, and in the process learn about Python's excellent\nPydata and related projects: numpy, pandas, and pytables.\n\nA recommendation engine is a software system that analyzes large amounts\nof transactional data and distills personal profiles to present its\nusers with relevant products/information/content.\n",
  "tags": [
    "tutorial"
  ],
  "thumbnail_url": "https://i.ytimg.com/vi/Qn4TWFtj7XI/hqdefault.jpg",
  "title": "A beginner's introduction to Pydata: how to build a minimal recommendation engine.",
  "videos": [
    {
      "type": "mp4",
      "url": "http://s3.us.archive.org/nextdayvideo/psf/pycon2013/A_beginners_introduction_to_Py.mp4?Signature=wYHYyyBePWmZCtYM4TAnwklMEwc%3D&Expires=1364913604&AWSAccessKeyId=FEWGReWX3QbNk0h3"
    },
    {
      "length": 0,
      "type": "youtube",
      "url": "https://www.youtube.com/watch?v=IjRy7dAWFdk"
    }
  ]
}
