{
  "copyright_text": null,
  "description": "",
  "duration": 2556,
  "language": null,
  "recorded": "2018-04-20",
  "related_urls": [
    {
      "label": "Conference schedule",
      "url": "https://www.pycon.it/p3/schedule/pycon9/"
    }
  ],
  "speakers": [],
  "tags": [],
  "thumbnail_url": "https://i.ytimg.com/vi/RhtXHI5KRzw/maxresdefault.jpg",
  "title": "A. Bassett - When your wetware has too many threads: Tips on how to improve your focus",
  "videos": [
    {
      "type": "youtube",
      "url": "https://www.youtube.com/watch?v=RhtXHI5KRzw"
    }
  ]
}
